nitk/__init__.py
nitk/clime.py
nitk/correlation_permuter.py
nitk/d_trace.py
nitk/l2_penalized_estimator.py
nitk/methods.py
nitk/scaled_lasso.py
nitk/scio.py
nitk/space.py
nitk-0.1.dist-info/METADATA
nitk-0.1.dist-info/RECORD
nitk-0.1.dist-info/WHEEL
nitk-0.1.dist-info/top_level.txt
