Metadata-Version: 2.1
Name: nitk
Version: 0.1
Summary: A package for inferring sparse partial correlation networks
Home-page: https://github.com/shazzzm/nitk
Author: Tristan Millington
Author-email: tristan.millington@gmail.com
License: UNKNOWN
Platform: UNKNOWN
Classifier: Programming Language :: Python :: 3
Classifier: License :: OSI Approved :: GNU General Public License v3 (GPLv3)
Classifier: Operating System :: OS Independent
Classifier: Development Status :: 2 - Pre-Alpha
